invocare/puppet/__init__.py
invocare/puppet/_version.py
invocare/puppet/agent.py
invocare_puppet-0.3.0.dist-info/DESCRIPTION.rst
invocare_puppet-0.3.0.dist-info/METADATA
invocare_puppet-0.3.0.dist-info/RECORD
invocare_puppet-0.3.0.dist-info/WHEEL
invocare_puppet-0.3.0.dist-info/metadata.json
invocare_puppet-0.3.0.dist-info/top_level.txt
