Metadata-Version: 2.0
Name: invocare-puppet
Version: 0.3.0
Summary: Puppet Invocations
Home-page: https://github.com/jbronn/invocare-puppet
Author: Justin Bronn
Author-email: jbronn@gmail.com
License: Apache License 2.0
Download-URL: https://pypi.python.org/pypi/invocare-puppet/
Platform: UNKNOWN
Classifier: Development Status :: 4 - Beta
Classifier: Intended Audience :: Developers
Classifier: Intended Audience :: System Administrators
Classifier: License :: OSI Approved :: Apache Software License
Classifier: Programming Language :: Python
Classifier: Programming Language :: Python :: 2
Classifier: Programming Language :: Python :: 3
Requires-Dist: invocare-ssh (>=0.3.0,<1.0.0)
